{
  "contents": {
    "source": "플레이타운",
    "category": "일상/소통",
    "solved_copyright": "DIA TV",
    "origin_lang": "KO",
    "fi_source_filename": "다크소울 한국1등 여성 고인물분이 저희집에 왔습니다ㄷㄷ.mp4",
    "fi_source_filepath": "https://objectstorage.ap-seoul-1.oraclecloud.com/n/cnb97trxvnun/b/clive-resource/o/contents/다크소울 한국1등 여성 고인물분이 저희집에 왔습니다ㄷㄷ.mp4",
    "li_platform_info": "DIA TV",
    "li_subject": "일상/소통",
    "li_summary": "다크소울 한국1등 여성 고인물분이 저희집에 왔습니다ㄷㄷ 다크소울에 대한 모든걸 전파해주는 여성 고인물의 플레이를 감상하세요",
    "li_location": "실내",
    "text_info": [
      {
        "fi_sound_filename": "002000_다크소울 한국1등 여성 고인물분이 저희집에 왔습니다ㄷㄷ/17.894999836808147_18.929998336997297_002000_다크소울 한국1등 여성 고인물분이 저희집에 왔습니다ㄷㄷ.wav",
        "fi_sound_filepath": "https://objectstorage.ap-seoul-1.oraclecloud.com/n/cnb97trxvnun/b/clive-resource/o/contents/다크소울 한국1등 여성 고인물분이 저희집에 왔습니다ㄷㄷ/002000_다크소울 한국1등 여성 고인물분이 저희집에 왔습니다ㄷㄷ/17.894999836808147_18.929998336997297_002000_다크소울 한국1등 여성 고인물분이 저희집에 왔습니다ㄷㄷ.wav",
        "fi_start_sound_time": "177.27999999999997",
        "fi_end_sound_time": "182.07999999999998",
        "fi_start_voice_time": "177.27999999999997",
        "fi_end_voice_time": "182.07999999999998",
        "li_speaker_info": {
          "gender": "남성",
          "ageGroup": "30대-50대 미만"
        },
        "tc_text": "그것도 없어가지고",
        "tl_trans_lang": "ZH",
        "tl_trans_text": "那个也没有",
        "tl_back_trans_lang": "KO",
        "tl_back_trans_text": "그것도 없고",
        "sl_new_word": [],
        "sl_abbreviation_word": [],
        "sl_slang": [],
        "sl_mistake": [],
        "sl_again": [],
        "sl_interjection": [],
        "en_outside": "",
        "en_inside": "",
        "en_day": "X",
        "en_night": "O"
      }
    ]
  }
}
